How2jGongjuHeZhongjianjianJiaocheng/README.md
How2jGongjuHeZhongjianjianJiaocheng/__init__.py
How2jGongjuHeZhongjianjianJiaocheng/__main__.py
How2jGongjuHeZhongjianjianJiaocheng/file.epub
How2jGongjuHeZhongjianjianJiaocheng/index.html
How2jGongjuHeZhongjianjianJiaocheng/css/__init__.py
How2jGongjuHeZhongjianjianJiaocheng/css/annotations.css
How2jGongjuHeZhongjianjianJiaocheng/css/main.css
How2jGongjuHeZhongjianjianJiaocheng/css/normalize.css
How2jGongjuHeZhongjianjianJiaocheng/css/popup.css
How2jGongjuHeZhongjianjianJiaocheng/font/__init__.py
How2jGongjuHeZhongjianjianJiaocheng/font/fontello.eot
How2jGongjuHeZhongjianjianJiaocheng/font/fontello.svg
How2jGongjuHeZhongjianjianJiaocheng/font/fontello.ttf
How2jGongjuHeZhongjianjianJiaocheng/font/fontello.woff
How2jGongjuHeZhongjianjianJiaocheng/img/__init__.py
How2jGongjuHeZhongjianjianJiaocheng/img/annotator-glyph-sprite.png
How2jGongjuHeZhongjianjianJiaocheng/img/annotator-icon-sprite.png
How2jGongjuHeZhongjianjianJiaocheng/img/apple-touch-icon.png
How2jGongjuHeZhongjianjianJiaocheng/img/cancelfullscreen.png
How2jGongjuHeZhongjianjianJiaocheng/img/close.png
How2jGongjuHeZhongjianjianJiaocheng/img/fullscreen.png
How2jGongjuHeZhongjianjianJiaocheng/img/loader.gif
How2jGongjuHeZhongjianjianJiaocheng/img/menu-icon.png
How2jGongjuHeZhongjianjianJiaocheng/img/save.png
How2jGongjuHeZhongjianjianJiaocheng/img/saved.png
How2jGongjuHeZhongjianjianJiaocheng/img/settings-s.png
How2jGongjuHeZhongjianjianJiaocheng/img/settings.png
How2jGongjuHeZhongjianjianJiaocheng/img/star.png
How2jGongjuHeZhongjianjianJiaocheng/js/__init__.py
How2jGongjuHeZhongjianjianJiaocheng/js/epub.js
How2jGongjuHeZhongjianjianJiaocheng/js/epub.min.js
How2jGongjuHeZhongjianjianJiaocheng/js/epub.min.map
How2jGongjuHeZhongjianjianJiaocheng/js/hooks.min.js
How2jGongjuHeZhongjianjianJiaocheng/js/hooks.min.map
How2jGongjuHeZhongjianjianJiaocheng/js/reader.js
How2jGongjuHeZhongjianjianJiaocheng/js/reader.js.map
How2jGongjuHeZhongjianjianJiaocheng/js/reader.min.js
how2j_gongju_he_zhongjianjian_jiaocheng-2024.3.5.0.dist-info/METADATA
how2j_gongju_he_zhongjianjian_jiaocheng-2024.3.5.0.dist-info/WHEEL
how2j_gongju_he_zhongjianjian_jiaocheng-2024.3.5.0.dist-info/entry_points.txt
how2j_gongju_he_zhongjianjian_jiaocheng-2024.3.5.0.dist-info/top_level.txt
how2j_gongju_he_zhongjianjian_jiaocheng-2024.3.5.0.dist-info/RECORD
